agoras/__init__.py
agoras/cli.py
agoras/api/__init__.py
agoras/api/publish.py
agoras/core/__init__.py
agoras/core/facebook.py
agoras/core/instagram.py
agoras/core/linkedin.py
agoras/core/logger.py
agoras/core/twitter.py
agoras/core/utils.py
agoras-1.1.3.dist-info/AUTHORS.rst
agoras-1.1.3.dist-info/LICENSE
agoras-1.1.3.dist-info/METADATA
agoras-1.1.3.dist-info/WHEEL
agoras-1.1.3.dist-info/entry_points.txt
agoras-1.1.3.dist-info/top_level.txt
agoras-1.1.3.dist-info/RECORD
