Metadata-Version: 2.1
Name: agoras
Version: 1.1.3
Summary: A command line python utility to manage your social networks (Twitter, Facebook, LinkedIn and Instagram)
Home-page: https://github.com/LuisAlejandro/agoras
Author: Luis Alejandro Martínez Faneyth
Author-email: luis@luisalejandro.org
Keywords: social networks,twitter,facebook,instagram,linkedin
Classifier: Development Status :: 5 - Production/Stable
Classifier: Intended Audience :: Developers
Classifier: License :: OSI Approved :: GNU General Public License v3 (GPLv3)
Classifier: Natural Language :: English
Classifier: Programming Language :: Python :: 3
Classifier: Programming Language :: Python :: 3.9
Classifier: Programming Language :: Python :: 3.10
Classifier: Programming Language :: Python :: 3.11
License-File: LICENSE
License-File: AUTHORS.rst
Requires-Dist: atoma ==0.0.17
Requires-Dist: tweepy ==4.14.0
Requires-Dist: python-facebook-api ==0.17.0
Requires-Dist: gspread ==5.10.0
Requires-Dist: google-auth ==2.22.0
Requires-Dist: python-dateutil ==2.8.2
Requires-Dist: filetype ==1.2.0
Requires-Dist: linkedin-api-client ==0.3.0
Requires-Dist: requests ==2.31.0
Requires-Dist: beautifulsoup4 ==4.12.2
